{
  "posts": [
    {
      "slug": "kenapa-butuh-dana-darurat",
      "title": "Kenapa Kamu Butuh Dana Darurat Sebelum Investasi?",
      "category": "personal_finance",
      "categoryLabel": "Personal Finance",
      "date": "2026-03-01",
      "excerpt": "Banyak orang langsung terjun ke investasi tanpa punya dana darurat. Padahal, urutan ini sangat penting untuk stabilitas keuangan jangka panjang.",
      "readingTime": "5 min read",
      "author": "Philip Mulyana"
    },
    {
      "slug": "bbm-naik-efek-domino-dompet",
      "title": "BBM Naik Lagi — Efek Domino ke Dompet Kamu",
      "category": "personal_finance",
      "categoryLabel": "News Insight",
      "date": "2026-03-01",
      "excerpt": "Pertamax naik ke Rp 12.300, minyak dunia melonjak 10% karena konflik Iran.",
      "readingTime": "4 min read",
      "author": "Philip Mulyana"
    },
    {
      "slug": "asuransi-jiwa-101",
      "title": "Asuransi Jiwa 101: Apa yang Perlu Kamu Tahu Sebelum Beli",
      "category": "insurance",
      "categoryLabel": "Insurance",
      "date": "2026-02-25",
      "excerpt": "Term life, whole life, unit link — bingung? Panduan lengkap untuk memahami jenis asuransi jiwa dan memilih yang tepat untuk situasimu.",
      "readingTime": "7 min read",
      "author": "Philip Mulyana"
    }
  ]
}